[
  {
    "id": "fc-law-09-01-01",
    "subject": "bookkeeping-law",
    "front": "記帳士職業倫理道德規範的制定機關？",
    "back": "中華民國記帳士公會全國聯合會（102年12月4日會員代表大會通過），非國家立法機關。",
    "material_ref": "law-09-01",
    "verified_at": "2026-07-05"
  },
  {
    "id": "fc-law-09-01-02",
    "subject": "bookkeeping-law",
    "front": "記帳士法 vs 記帳士職業倫理道德規範的制定機關？",
    "back": "記帳士法：立法院（總統公布）。職業倫理道德規範：記帳士公會全國聯合會。",
    "material_ref": "law-09-01",
    "verified_at": "2026-07-05"
  },
  {
    "id": "fc-law-09-01-03",
    "subject": "bookkeeping-law",
    "front": "規範的適用對象？",
    "back": "提供記帳士服務之個人及個體，即本會會員公會之所屬會員。",
    "material_ref": "law-09-01",
    "verified_at": "2026-07-05"
  },
  {
    "id": "fc-law-09-01-04",
    "subject": "bookkeeping-law",
    "front": "未被明文規範的行為是否可能受紀律處分？",
    "back": "可能，未規範之特定行為仍可能被視為不可接受或不名譽之行為而受紀律處分。",
    "material_ref": "law-09-01",
    "verified_at": "2026-07-05"
  },
  {
    "id": "fc-law-09-01-05",
    "subject": "bookkeeping-law",
    "front": "規範的兩個構成要素？",
    "back": "基本原則（攸關專業實務）與行為準則（表達行為標準期望，解釋基本原則的實際應用）。",
    "material_ref": "law-09-01",
    "verified_at": "2026-07-05"
  },
  {
    "id": "fc-law-09-01-06",
    "subject": "bookkeeping-law",
    "front": "規範制定的目的？",
    "back": "砥礪記帳士專業之道德文化。",
    "material_ref": "law-09-01",
    "verified_at": "2026-07-05"
  }
]
